{
  "aor": 0.0011266371681415929,
  "aqi": 0.023195230973451327,
  "bids_meta": {
    "EchoTime": 0.027,
    "FlipAngle": 64,
    "RepetitionTime": 2.08,
    "SliceTiming": [
      0,
      1.0575,
      0.0575,
      1.115,
      0.1125,
      1.17,
      0.1675,
      1.225,
      0.2225,
      1.2825,
      0.28,
      1.3375,
      0.335,
      1.3925,
      0.39,
      1.4475,
      0.4475,
      1.505,
      0.5025,
      1.56,
      0.5575,
      1.615,
      0.6125,
      1.67,
      0.67,
      1.7275,
      0.725,
      1.7825,
      0.78,
      1.8375,
      0.835,
      1.8925,
      0.8925,
      1.95,
      0.9475,
      2.005,
      1.0025
    ],
    "TaskName": "Funcational localizer",
    "dataset": "ds001612",
    "modality": "bold",
    "run_id": 2,
    "subject_id": "19",
    "task_id": "loc"
  },
  "dummy_trs": 1,
  "dvars_nstd": 31.50769680431111,
  "dvars_std": 1.0679562938222218,
  "dvars_vstd": 0.944658419333333,
  "efc": 0.5973503310878654,
  "fber": 1099.080810546875,
  "fd_mean": 0.19519477785539263,
  "fd_num": 60,
  "fd_perc": 26.548672566371682,
  "fwhm_avg": 1.7203277777777777,
  "fwhm_x": 1.6605133333333333,
  "fwhm_y": 1.8056833333333333,
  "fwhm_z": 1.6947866666666667,
  "gcor": 0.0091098,
  "gsr_x": -0.002843176946043968,
  "gsr_y": 0.027138013392686844,
  "provenance": {
    "md5sum": "d8a6b464d2228d23be2a78cf82ba4317",
    "settings": {
      "fd_thres": 0.2,
      "testing": false
    },
    "software": "mriqc",
    "version": "22.0.6",
    "webapi_port": null,
    "webapi_url": "https://mriqc.nimh.nih.gov/api/v1"
  },
  "size_t": 226,
  "size_x": 64,
  "size_y": 64,
  "size_z": 37,
  "snr": 5.691024385812283,
  "spacing_tr": 2.0799999237060547,
  "spacing_x": 3.0,
  "spacing_y": 3.0,
  "spacing_z": 3.0,
  "summary_bg_k": 21.78552768850266,
  "summary_bg_mad": 12.615238617797107,
  "summary_bg_mean": 40.644718170166016,
  "summary_bg_median": 19.238937377929688,
  "summary_bg_n": 77137.0,
  "summary_bg_p05": 9.0,
  "summary_bg_p95": 144.91592407226523,
  "summary_bg_stdv": 63.33088684082031,
  "summary_fg_k": 1.738972437159834,
  "summary_fg_mad": 112.56619337843397,
  "summary_fg_mean": 672.59228515625,
  "summary_fg_median": 657.6416015625,
  "summary_fg_n": 39891.0,
  "summary_fg_p05": 520.3805236816406,
  "summary_fg_p95": 871.9712219238281,
  "summary_fg_stdv": 115.55623626708984,
  "tsnr": 40.27777767274529
}