{
  "aor": 0.0017846875,
  "aqi": 0.010174269598214285,
  "bids_meta": {
    "EchoTime": 0.027,
    "FlipAngle": 64,
    "RepetitionTime": 2.08,
    "SliceTiming": [
      0,
      1.0575,
      0.0575,
      1.115,
      0.1125,
      1.17,
      0.1675,
      1.225,
      0.2225,
      1.2825,
      0.28,
      1.3375,
      0.335,
      1.3925,
      0.39,
      1.4475,
      0.4475,
      1.505,
      0.5025,
      1.56,
      0.5575,
      1.615,
      0.6125,
      1.67,
      0.67,
      1.7275,
      0.725,
      1.7825,
      0.78,
      1.8375,
      0.835,
      1.8925,
      0.8925,
      1.95,
      0.9475,
      2.005,
      1.0025
    ],
    "TaskName": "Funcational localizer",
    "dataset": "ds001612",
    "modality": "bold",
    "run_id": 2,
    "subject_id": "12",
    "task_id": "loc"
  },
  "dummy_trs": 0,
  "dvars_nstd": 24.56848531094169,
  "dvars_std": 1.159166830762332,
  "dvars_vstd": 0.9880335869058295,
  "efc": 0.6106934788963972,
  "fber": 1424.7947998046875,
  "fd_mean": 0.1384550031862923,
  "fd_num": 37,
  "fd_perc": 16.517857142857142,
  "fwhm_avg": 1.7323688888888888,
  "fwhm_x": 1.6240666666666668,
  "fwhm_y": 1.8158166666666666,
  "fwhm_z": 1.7572233333333334,
  "gcor": 0.0136528,
  "gsr_x": -0.009895467199385166,
  "gsr_y": 0.04350629448890686,
  "provenance": {
    "md5sum": "ed1e0a40c24a6263961d8cb99240dccf",
    "settings": {
      "fd_thres": 0.2,
      "testing": false
    },
    "software": "mriqc",
    "version": "22.0.6",
    "webapi_port": null,
    "webapi_url": "https://mriqc.nimh.nih.gov/api/v1"
  },
  "size_t": 224,
  "size_x": 64,
  "size_y": 64,
  "size_z": 37,
  "snr": 6.1109316764920925,
  "spacing_tr": 2.0799999237060547,
  "spacing_x": 3.0,
  "spacing_y": 3.0,
  "spacing_z": 3.0,
  "summary_bg_k": 20.5458764979999,
  "summary_bg_mad": 12.277799621999517,
  "summary_bg_mean": 50.60975646972656,
  "summary_bg_median": 20.616071701049805,
  "summary_bg_n": 74863.0,
  "summary_bg_p05": 10.084821701049805,
  "summary_bg_p95": 203.52635345458955,
  "summary_bg_stdv": 81.82648468017578,
  "summary_fg_k": 3.7873532547571536,
  "summary_fg_mad": 119.83269977175783,
  "summary_fg_mean": 818.552734375,
  "summary_fg_median": 803.7678833007812,
  "summary_fg_n": 41709.0,
  "summary_fg_p05": 653.7152099609375,
  "summary_fg_p95": 1033.867919921875,
  "summary_fg_stdv": 131.52793884277344,
  "tsnr": 62.063693346921355
}