{
  "aor": 0.0026552162849872774,
  "aqi": 0.010345946183206105,
  "bids_meta": {
    "EchoTime": 0.027,
    "FlipAngle": 64,
    "RepetitionTime": 2.08,
    "SliceTiming": [
      0,
      1.0575,
      0.055,
      1.1125,
      0.1125,
      1.17,
      0.1675,
      1.225,
      0.2225,
      1.28,
      0.2775,
      1.3375,
      0.335,
      1.3925,
      0.39,
      1.4475,
      0.445,
      1.5025,
      0.5025,
      1.56,
      0.5575,
      1.615,
      0.6125,
      1.67,
      0.6675,
      1.725,
      0.725,
      1.7825,
      0.78,
      1.8375,
      0.835,
      1.8925,
      0.89,
      1.9475,
      0.9475,
      2.005,
      1.0025
    ],
    "TaskName": "Main task",
    "dataset": "ds001612",
    "modality": "bold",
    "run_id": 4,
    "subject_id": "05",
    "task_id": "main"
  },
  "dummy_trs": 1,
  "dvars_nstd": 24.20304754811224,
  "dvars_std": 1.0966433285714297,
  "dvars_vstd": 1.0218967324744899,
  "efc": 0.6196283934480433,
  "fber": 1144.918701171875,
  "fd_mean": 0.10840070299044562,
  "fd_num": 29,
  "fd_perc": 7.379134860050891,
  "fwhm_avg": 1.7602988888888886,
  "fwhm_x": 1.6232333333333333,
  "fwhm_y": 1.9007966666666667,
  "fwhm_z": 1.7568666666666666,
  "gcor": 0.0116519,
  "gsr_x": -0.00648691039532423,
  "gsr_y": 0.04890585318207741,
  "provenance": {
    "md5sum": "18f12d430a03c69bfe2e86edbaf2ae5f",
    "settings": {
      "fd_thres": 0.2,
      "testing": false
    },
    "software": "mriqc",
    "version": "22.0.6",
    "webapi_port": null,
    "webapi_url": "https://mriqc.nimh.nih.gov/api/v1"
  },
  "size_t": 393,
  "size_x": 64,
  "size_y": 64,
  "size_z": 37,
  "snr": 5.228900292810115,
  "spacing_tr": 2.0799999237060547,
  "spacing_x": 3.0,
  "spacing_y": 3.0,
  "spacing_z": 3.0,
  "summary_bg_k": 34.56655800638007,
  "summary_bg_mad": 12.285226941958975,
  "summary_bg_mean": 46.423423767089844,
  "summary_bg_median": 20.08905792236328,
  "summary_bg_n": 73396.0,
  "summary_bg_p05": 10.353689193725586,
  "summary_bg_p95": 163.29580688476562,
  "summary_bg_stdv": 68.1653060913086,
  "summary_fg_k": 3.0627307914073034,
  "summary_fg_mad": 123.57092236377295,
  "summary_fg_mean": 734.388671875,
  "summary_fg_median": 716.2557373046875,
  "summary_fg_n": 42952.0,
  "summary_fg_p05": 562.6900817871094,
  "summary_fg_p95": 967.2652618408202,
  "summary_fg_stdv": 136.9785919189453,
  "tsnr": 52.97672196174972
}